{
  "name": "promethean-engine",
  "version": "0.1.0",
  "description": "A modular 2D game engine with SDL2 and OpenGL backend.",
  "dependencies": [
    {
      "name": "sdl2",
      "default-features": true
    },
    {
      "name": "openal-soft",
      "default-features": true
    },
    {
      "name": "spdlog",
      "default-features": true
    },
    {
      "name": "nlohmann-json",
      "version>=": "3.11.3"
    }
  ],
  "overrides": [
    {
      "name": "nlohmann-json",
      "version": "3.11.3"
    }
  ],
  "builtin-baseline": "6dbdfb2d2d47ba6d8084cf022e86bc5d6520eb80"
}
